baka_armor/__init__.py
baka_armor/assets.py
baka_armor/config.py
baka_armor/ui/__init__.py
baka_armor/ui/common.py
baka_armor/ui/directive.py
baka_armor/ui/fields.py
baka_armor/ui/helpers.py
baka_armor/ui/utils.py
baka_armor-0.1.dev1.dist-info/DESCRIPTION.rst
baka_armor-0.1.dev1.dist-info/METADATA
baka_armor-0.1.dev1.dist-info/RECORD
baka_armor-0.1.dev1.dist-info/WHEEL
baka_armor-0.1.dev1.dist-info/metadata.json
baka_armor-0.1.dev1.dist-info/top_level.txt
example/__init__.py
example/__main__.py
