Metadata-Version: 2.0
Name: baka-armor
Version: 0.1.dev1
Summary: Assets for Baka and Pyramid
Home-page: https://github.com/baka-framework/baka_armor
Author: Nanang Suryadi
Author-email: nanang.jobs@gmail.com
License: MIT
Keywords: webpack,webassets,baka assets,pyramid assets
Platform: UNKNOWN
Classifier: Development Status :: 5 - Production/Stable
Classifier: Intended Audience :: Developers
Classifier: License :: OSI Approved :: MIT License
Classifier: Programming Language :: Python :: 2.7
Classifier: Programming Language :: Python :: 3.3
Classifier: Programming Language :: Python :: 3.4
Classifier: Programming Language :: Python :: 3.5
Classifier: Programming Language :: Python :: 3.6
Requires-Dist: pyramid
Requires-Dist: webassets
Requires-Dist: trafaret
Requires-Dist: WebHelpers2
Requires-Dist: pytz
Requires-Dist: python-dateutil
Requires-Dist: bitmath
Requires-Dist: Babel
Requires-Dist: pyScss
Requires-Dist: PyExecJS
Requires-Dist: jsmin
Requires-Dist: cssmin
Requires-Dist: plim
